gamma_spectroscopy/__init__.py
gamma_spectroscopy/fake_picoscope.py
gamma_spectroscopy/gamma_spectroscopy_gui.py
gamma_spectroscopy/gamma_spectroscopy_gui.ui
gamma_spectroscopy/picoscope_5000a.py
gamma_spectroscopy-1.1.dist-info/LICENSE
gamma_spectroscopy-1.1.dist-info/METADATA
gamma_spectroscopy-1.1.dist-info/WHEEL
gamma_spectroscopy-1.1.dist-info/entry_points.txt
gamma_spectroscopy-1.1.dist-info/top_level.txt
gamma_spectroscopy-1.1.dist-info/RECORD
