Metadata-Version: 2.1
Name: gamma-spectroscopy
Version: 1.1
Summary: A GUI for gamma spectroscopy using a PicoScope
Home-page: https://github.com/davidfokkema/gamma-spectroscopy
Author: David Fokkema
Author-email: davidfokkema@icloud.com
License: UNKNOWN
Platform: UNKNOWN
Classifier: Development Status :: 4 - Beta
Classifier: Intended Audience :: Science/Research
Classifier: Topic :: Scientific/Engineering :: Physics
Classifier: Programming Language :: Python :: 3
Classifier: License :: OSI Approved :: GNU General Public License v3 (GPLv3)
Classifier: Operating System :: Microsoft :: Windows
Classifier: Operating System :: MacOS :: MacOS X
Classifier: Operating System :: POSIX :: Linux
